thebe/.DS_Store
thebe/.livepy.py.swn
thebe/.livepy.py.swo
thebe/.test.py.swo
thebe/.thebe.py.swp
thebe/.util.py.swn
thebe/.util.py.swo
thebe/__init__.py
thebe/database.sqlite
thebe/tags
thebe/thebe.py
thebe/util.py
thebe/__pycache__/db.cpython-37.pyc
thebe/__pycache__/ttest.cpython-37.pyc
thebe/__pycache__/util.cpython-37.pyc
thebe/core/__init__.py
thebe/core/args.py
thebe/core/constants.py
thebe/core/data.py
thebe/core/database.py
thebe/core/database.sqlite
thebe/core/file.py
thebe/core/fileController.py
thebe/core/html.py
thebe/core/ipynb.py
thebe/core/jupyter_wrapper.py
thebe/core/logger.py
thebe/core/output.py
thebe/core/run.py
thebe/core/update.py
thebe/core/vim.py
thebe/core/logs/database.log
thebe/core/logs/executionrecord.log
thebe/core/logs/run.log
thebe/core/logs/sockets.log
thebe/logs/all.py
thebe/static/__init__.py
thebe/static/favicon.ico
thebe/static/main.js
thebe/static/socket.io.slim.js
thebe/static/styles.css
thebe/static/test.py
thebe/static/thebe_icon.PNG
thebe/static/vue.min.js
thebe/static/__pycache__/__init__.cpython-37.pyc
thebe/static/__pycache__/test.cpython-37.pyc
thebe/static/highlight/.DS_Store
thebe/static/highlight/highlight.pack.js
thebe/static/highlight/styles/a11y-dark.css
thebe/static/highlight/styles/a11y-light.css
thebe/static/highlight/styles/agate.css
thebe/static/highlight/styles/an-old-hope.css
thebe/static/highlight/styles/androidstudio.css
thebe/static/highlight/styles/arduino-light.css
thebe/static/highlight/styles/arta.css
thebe/static/highlight/styles/ascetic.css
thebe/static/highlight/styles/atelier-cave-dark.css
thebe/static/highlight/styles/atelier-cave-light.css
thebe/static/highlight/styles/atelier-dune-dark.css
thebe/static/highlight/styles/atelier-dune-light.css
thebe/static/highlight/styles/atelier-estuary-dark.css
thebe/static/highlight/styles/atelier-estuary-light.css
thebe/static/highlight/styles/atelier-forest-dark.css
thebe/static/highlight/styles/atelier-forest-light.css
thebe-0.0.4.6.dist-info/LICENSE
thebe-0.0.4.6.dist-info/METADATA
thebe-0.0.4.6.dist-info/WHEEL
thebe-0.0.4.6.dist-info/entry_points.txt
thebe-0.0.4.6.dist-info/top_level.txt
thebe-0.0.4.6.dist-info/RECORD
