Metadata-Version: 2.1
Name: thebe
Version: 0.0.4.6
Summary: Automatically runs and displays python code in browser.
Home-page: https://github.com/hotsoupisgood/Satyrn
Author-email: hairyhenry@gmail.com
License: UNKNOWN
Platform: UNKNOWN
Classifier: Programming Language :: Python :: 3
Classifier: License :: OSI Approved :: MIT License
Classifier: Operating System :: OS Independent
Requires-Python: >=3.7
Requires-Dist: flask
Requires-Dist: flask-socketio
Requires-Dist: pygments
Requires-Dist: dill
Requires-Dist: pypandoc
Requires-Dist: jupyter-client
